cli/__init__.py
cli/__main__.py
commands/__init__.py
commands/clean.py
commands/export.py
commands/import.py
commands/list.py
utils/__init__.py
utils/db.py
utils/stdout.py
databricks_workspace_tool-0.1.4.dist-info/LICENSE
databricks_workspace_tool-0.1.4.dist-info/METADATA
databricks_workspace_tool-0.1.4.dist-info/WHEEL
databricks_workspace_tool-0.1.4.dist-info/entry_points.txt
databricks_workspace_tool-0.1.4.dist-info/top_level.txt
databricks_workspace_tool-0.1.4.dist-info/RECORD
