Metadata-Version: 2.1
Name: databricks-workspace-tool
Version: 0.1.4
Summary: Tool to manage notebooks and clean output cells.
Home-page: https://github.com/frogrammer/databricks-workspace-tool
Author: Luke Vinton
Author-email: luke0vinton@gmail.com
License: Apache 2.0
Platform: UNKNOWN
Requires-Dist: fire
Requires-Dist: databricks-cli
Requires-Dist: fire-cli-helper
Requires-Dist: gitpython
